ip2instance/__init__.py
ip2instance-1.2.2.dist-info/entry_points.txt
ip2instance-1.2.2.dist-info/DESCRIPTION.rst
ip2instance-1.2.2.dist-info/RECORD
ip2instance-1.2.2.dist-info/metadata.json
ip2instance-1.2.2.dist-info/WHEEL
ip2instance-1.2.2.dist-info/METADATA
ip2instance-1.2.2.dist-info/top_level.txt
