Metadata-Version: 2.0
Name: ip2instance
Version: 1.2.2
Summary: Search through multiple AWS accounts for instance IP addresses
Home-page: https://github.com/gene1wood/ip2instance
Author: Gene Wood
Author-email: gene_wood@cementhorizon.com
License: MPL 2.0
Keywords: aws ec2
Platform: UNKNOWN
Classifier: Development Status :: 3 - Alpha
Classifier: Intended Audience :: Developers
Classifier: Topic :: System :: Systems Administration
Classifier: License :: OSI Approved :: Mozilla Public License 2.0 (MPL 2.0)
Classifier: Programming Language :: Python :: 2.7
Requires-Dist: boto
Requires-Dist: PyYAML
